{
    "backend": "api-server-django",
    "db_name": "",
    "db_pass": "",
    "db_type": "sqlite",
    "db_user": "",
    "dbms": "1",
    "description": "generated product",
    "design": "purity-dashboard",
    "docker": "1",
    "err_code": 0,
    "frontend": "react",
    "heroku": "0",
    "pattern": "fullstack",
    "pro": "0",
    "task_id": "e241ffb0-ab56-4001-9cfe-7731983e2713",
    "task_info": "Upload Sources [0%] - 209 files",
    "task_output": "e241ffb0-ab56-4001-9cfe-7731983e2713.zip",
    "task_result": "SUCCESS",
    "task_state": "RUNNING",
    "task_ts_end": "2024-07-22-15-56-34",
    "task_ts_start": "2024-07-22-15-56-33"
}